{"is_source_file": false, "format": "", "description": "", "external_files": [], "external_methods": [], "published": [], "classes": [], "methods": [], "calls": [], "search-terms": ["PostgreSQL schema", "quiz database", "connections", "schema definition", "seed data"], "state": 2, "file_id": 8, "knowledge_revision": 21, "git_revision": "e1e6a7de331828b1d6cea9491599cc5d2123ef9e", "hash": "79e00fdcb23d26cc385ffe5e0cd17b36", "format-version": 4, "code-base-name": "quiz_database", "filename": "quiz_database/SCHEMA_README.md", "revision_history": [{"21": "e1e6a7de331828b1d6cea9491599cc5d2123ef9e"}]}